example/alu.v
module alu(A,B,ALUop,C);
    input [31:0] A,B;
    input [2:0] ALUop;
    output reg [31:0] C;
    always @(A or B or ALUop) begin
        case(ALUop)
            3'b000: C = A + B; // add
            3'b001: C = A - B; // sub
            3'b010: C = A & B; // and
            3'b011: C = A | B; // or
            default: C = 0;
        endcase
    end
endmodule

example/test.v
`timescale 1ms/1ms
module test();
    reg [31:0] A,B;
    wire [31:0] C;
    reg [2:0] ALUop;
    reg [10:0] cnt;
    alu myalu(.A(A),.B(B),.ALUop(ALUop),.C(C));
    initial begin
        $dumpfile("test.vcd");
        $dumpvars;
        $display("TEST");
        A=32'h0d000721;
        B=32'hdeadbeef;
        ALUop=3'b000;
        cnt=10'b0;
        #(100) $finish;
    end
    always begin
        #(5) ALUop^=3'b001;
        cnt+=1;
    end
endmodule

example/test.vcd
$date
	Fri Mar  6 10:50:10 2026
$end
$version
	Icarus Verilog
$end
$timescale
	1ms
$end
$scope module test $end
$var wire 32 ! C [31:0] $end
$var reg 32 " A [31:0] $end
$var reg 3 # ALUop [2:0] $end
$var reg 32 $ B [31:0] $end
$var reg 11 % cnt [10:0] $end
$scope module myalu $end
$var wire 32 & A [31:0] $end
$var wire 3 ' ALUop [2:0] $end
$var wire 32 ( B [31:0] $end
$var reg 32 ) C [31:0] $end
$upscope $end
$upscope $end
$enddefinitions $end
$comment Show the parameter values. $end
$dumpall
$end
#0
$dumpvars
b11101011101011011100011000010000 )
b11011110101011011011111011101111 (
b0 '
b1101000000000000011100100001 &
b0 %
b11011110101011011011111011101111 $
b0 #
b1101000000000000011100100001 "
b11101011101011011100011000010000 !
$end
#5
b101110010100100100100000110010 !
b101110010100100100100000110010 )
b1 %
b1 #
b1 '
#10
b11101011101011011100011000010000 !
b11101011101011011100011000010000 )
b10 %
b0 #
b0 '
#15
b101110010100100100100000110010 !
b101110010100100100100000110010 )
b11 %
b1 #
b1 '
#20
b11101011101011011100011000010000 !
b11101011101011011100011000010000 )
b100 %
b0 #
b0 '
#25
b101110010100100100100000110010 !
b101110010100100100100000110010 )
b101 %
b1 #
b1 '
#30
b11101011101011011100011000010000 !
b11101011101011011100011000010000 )
b110 %
b0 #
b0 '
#35
b101110010100100100100000110010 !
b101110010100100100100000110010 )
b111 %
b1 #
b1 '
#40
b11101011101011011100011000010000 !
b11101011101011011100011000010000 )
b1000 %
b0 #
b0 '
#45
b101110010100100100100000110010 !
b101110010100100100100000110010 )
b1001 %
b1 #
b1 '
#50
b11101011101011011100011000010000 !
b11101011101011011100011000010000 )
b1010 %
b0 #
b0 '
#55
b101110010100100100100000110010 !
b101110010100100100100000110010 )
b1011 %
b1 #
b1 '
#60
b11101011101011011100011000010000 !
b11101011101011011100011000010000 )
b1100 %
b0 #
b0 '
#65
b101110010100100100100000110010 !
b101110010100100100100000110010 )
b1101 %
b1 #
b1 '
#70
b11101011101011011100011000010000 !
b11101011101011011100011000010000 )
b1110 %
b0 #
b0 '
#75
b101110010100100100100000110010 !
b101110010100100100100000110010 )
b1111 %
b1 #
b1 '
#80
b11101011101011011100011000010000 !
b11101011101011011100011000010000 )
b10000 %
b0 #
b0 '
#85
b101110010100100100100000110010 !
b101110010100100100100000110010 )
b10001 %
b1 #
b1 '
#90
b11101011101011011100011000010000 !
b11101011101011011100011000010000 )
b10010 %
b0 #
b0 '
#95
b101110010100100100100000110010 !
b101110010100100100100000110010 )
b10011 %
b1 #
b1 '
#100
b11101011101011011100011000010000 !
b11101011101011011100011000010000 )
b10100 %
b0 #
b0 '
